handkerchief-0.2.dist-info/DESCRIPTION.rst
handkerchief-0.2.dist-info/metadata.json
handkerchief-0.2.dist-info/top_level.txt
handkerchief-0.2.dist-info/WHEEL
handkerchief-0.2.dist-info/METADATA
handkerchief-0.2.dist-info/entry_points.txt
handkerchief-0.2.dist-info/RECORD
handkerchief/issues-handkerchief.html
handkerchief/.handkerchief.py.swp
handkerchief/__init__.pyc
handkerchief/__init__.py
handkerchief/handkerchief.pyc
handkerchief/handkerchief.py
handkerchief/layouts/default/highlight.pack.js
handkerchief/layouts/default/default.js
handkerchief/layouts/default/marked.min.js
handkerchief/layouts/default/style.css
handkerchief/layouts/default/default.json
handkerchief/layouts/default/jquery-2.1.1.min.js
handkerchief/layouts/default/default.html
handkerchief/layouts/default/github.css
