Metadata-Version: 2.0
Name: handkerchief
Version: 0.2
Summary: simple offline issue reader for GitHub Issues
Home-page: https://github.com/jreinhardt/handkerchief
Author: Johannes Reinhardt
Author-email: jreinhardt@ist-dein-freund.de
License: MIT
Keywords: github,issues,offline
Platform: UNKNOWN
Classifier: Development Status :: 3 - Alpha
Classifier: License :: OSI Approved :: MIT License
Classifier: Operating System :: OS Independent
Classifier: Programming Language :: Python :: 2.7
Requires-Dist: Jinja2
Requires-Dist: requests
